nrepl/__init__.py
nrepl/_compat.py
nrepl/cli.py
nrepl/client.py
nrepl/clj.py
nrepl/proc.py
nrepl/utils.py
nrepl/watcher.py
nrepl-0.1.7.dist-info/LICENSE
nrepl-0.1.7.dist-info/METADATA
nrepl-0.1.7.dist-info/WHEEL
nrepl-0.1.7.dist-info/entry_points.txt
nrepl-0.1.7.dist-info/top_level.txt
nrepl-0.1.7.dist-info/RECORD
