Metadata-Version: 2.1
Name: nrepl
Version: 0.1.7
Summary: Auto reload class with Clojure nREPL
Home-page: https://github.com/shonenada/nREPL-reloader
Author: shonenada
Author-email: shonenada@gmail.com
License: UNKNOWN
Platform: any
Classifier: Environment :: Console
Classifier: Topic :: System :: Shells
Classifier: Intended Audience :: Developers
Classifier: License :: OSI Approved :: MIT License
Classifier: Operating System :: OS Independent
Classifier: Programming Language :: Python
Classifier: Programming Language :: Python :: 2
Classifier: Programming Language :: Python :: 3
Classifier: Development Status :: 3 - Alpha
